asynceth/__init__.py
asynceth/utils.py
asynceth/contract/__init__.py
asynceth/contract/contract.py
asynceth/contract/transaction.py
asynceth/contract/utils.py
asynceth/jsonrpc/__init__.py
asynceth/jsonrpc/aiohttp_client.py
asynceth/jsonrpc/client.py
asynceth/jsonrpc/errors.py
asynceth/jsonrpc/middleware.py
asynceth/jsonrpc/tornado_client.py
asynceth-0.0.12.dist-info/LICENSE
asynceth-0.0.12.dist-info/METADATA
asynceth-0.0.12.dist-info/WHEEL
asynceth-0.0.12.dist-info/top_level.txt
asynceth-0.0.12.dist-info/RECORD
