Metadata-Version: 2.1
Name: asynceth
Version: 0.0.12
Summary: Asyncio Ethereum Utilities
Home-page: https://github.com/tristan/asynceth
Author: Tristan King
Author-email: mail@tristan.sh
License: MIT
Platform: UNKNOWN
Classifier: Development Status :: 4 - Beta
Classifier: Intended Audience :: Developers
Classifier: License :: Public Domain
Classifier: Operating System :: OS Independent
Classifier: Programming Language :: Python
Classifier: Programming Language :: Python :: 3.6
Requires-Dist: regex
Requires-Dist: ethereum
Requires-Dist: eth-abi (>=2.0.0-beta.1)
